backup_compose/__init__.py
backup_compose/__main__.py
backup_compose/backup.py
backup_compose/models.py
backup_compose/restore.py
backup_compose/utils.py
backup_compose-0.0.4.dist-info/LICENSE
backup_compose-0.0.4.dist-info/METADATA
backup_compose-0.0.4.dist-info/WHEEL
backup_compose-0.0.4.dist-info/top_level.txt
backup_compose-0.0.4.dist-info/RECORD
