Metadata-Version: 2.1
Name: backup-compose
Version: 0.0.4
Summary: Backup/Restore your docker-compose projects
Home-page: https://github.com/beremaran/backup-compose
Author: Berke Arslan
Author-email: berke@beremaran.com
License: UNKNOWN
Project-URL: Bug Tracker, https://github.com/beremaran/backup-compose/issues
Platform: UNKNOWN
Classifier: Programming Language :: Python :: 3
Classifier: License :: OSI Approved :: MIT License
Classifier: Operating System :: OS Independent
Requires-Python: >=3.6
Requires-Dist: docker-compose
